RAM/ram_dualport_design.sv
module ram_design(input logic clk,
                  input logic en_a, en_b, //enable to write/read
                  input logic [4:0] addr_a, addr_b,
                  input logic [7:0] data_in_a, data_in_b,
                  output logic [7:0] data_out_a, data_out_b
                  );
  
  logic [7:0] ram [31:0];
  
  always@(posedge clk)   //port a
    if(en_a) begin
      ram [addr_a] <= data_in_a; //writing data in ram
      data_out_a <= data_in_a;
    end
    else begin 
      data_out_a <= ram [addr_a]; //read from ram
    end
  
  always@(posedge clk)  //port b
    if(en_b) begin
      ram [addr_b] <= data_in_b;
      data_out_b <= data_in_b;
    end
    else begin 
      data_out_b <= ram [addr_b];
    end
  
endmodule:ram_design

RAM/ram_dualport_testbench.sv
module ram_testbench;
  logic clk;
  logic en_a, en_b;
  logic [4:0] addr_a, addr_b;
  logic [7:0] data_in_a, data_in_b;
  logic [7:0] data_out_a, data_out_b;
  logic [7:0] out_a_tb, out_b_tb; //testbench outputs
  logic [7:0] ram [31:0];
  
  ram_design DUT(.clk(clk), 
                 .en_a(en_a), 
                 .en_b(en_b), 
                 .addr_a(addr_a), 
                 .addr_b(addr_b), 
                 .data_in_a(data_in_a), 
                 .data_in_b(data_in_b), 
                 .data_out_a(data_out_a), 
                 .data_out_b(data_out_b));
                
   initial begin
     clk = 0;
     forever #10 clk = ~clk;
   end 
  
   initial begin
     repeat (1) begin
        execute;
        en_a = 0;
        en_b = 0;
     end
     repeat (10) begin
        execute;
        en_a = 1;
        en_b = 1;
     end
     
     if(en_a) begin
       ram [addr_a] <= data_in_a; //attempt: to generate testbench outputs
      out_a_tb <= data_in_a;
     end
     else begin 
      out_a_tb <= ram [addr_a];
     end
     
     if(en_b) begin
      ram [addr_b] <= data_in_b;
      out_b_tb <= data_in_b;
     end
     else begin 
      out_b_tb <= ram [addr_b];
     end
     
   end

   task execute;
     begin
      @(posedge clk)
      addr_a = $random;
      data_in_a = $random;
      addr_b = $random;
      data_in_b = $random;    
      end
   endtask
  
  
   initial begin                    //comparing testbench outputs with design outputs
     if(!(out_a_tb == data_out_a) && (out_b_tb == data_out_b)) begin
       $display ($time," Transaction failed!\nDesign output A = %b, Testbench output A = %b \nDesign output B = %b, Testbench output B = %b",data_out_a,out_a_tb,data_out_b,out_b_tb);
     end
     else 
       $display ($time," Transaction successful");
     
     #180 $finish;
   end
  
   initial begin
     $dumpfile("ram.vcd");
     $dumpvars;
   end
  
endmodule:ram_testbench

RAM/ram.vcd
$date
	Tue Oct 17 14:02:05 2023
$end

$version
	Synopsys VCS version S-2021.09
$end

$timescale
	1ns
$end

$comment Csum: 1 3d94152d44433f9a $end


$scope module ram_testbench $end
$var reg 1 ! clk $end
$var reg 1 " en_a $end
$var reg 1 # en_b $end
$var reg 5 $ addr_a [4:0] $end
$var reg 5 % addr_b [4:0] $end
$var reg 8 & data_in_a [7:0] $end
$var reg 8 ' data_in_b [7:0] $end
$var reg 8 ( data_out_a [7:0] $end
$var reg 8 ) data_out_b [7:0] $end
$var reg 8 * out_a_tb [7:0] $end
$var reg 8 + out_b_tb [7:0] $end

$scope task execute $end
$upscope $end


$scope module DUT $end
$var reg 1 ! clk $end
$var reg 1 " en_a $end
$var reg 1 # en_b $end
$var reg 5 $ addr_a [4:0] $end
$var reg 5 % addr_b [4:0] $end
$var reg 8 & data_in_a [7:0] $end
$var reg 8 ' data_in_b [7:0] $end
$var reg 8 ( data_out_a [7:0] $end
$var reg 8 ) data_out_b [7:0] $end
$upscope $end

$upscope $end

$enddefinitions $end

#0
$dumpvars
0!
x"
x#
bxxxxx $
bxxxxx %
bxxxxxxxx &
bxxxxxxxx '
bxxxxxxxx (
bxxxxxxxx )
bxxxxxxxx *
bxxxxxxxx +
$end
#10
1!
b00100 $
b10000001 &
b01001 %
b01100011 '
0"
0#
#20
0!
#30
1!
b01101 $
b10001101 &
b00101 %
b00010010 '
1"
1#
b10001101 (
b00010010 )
#40
0!
#50
1!
b00001 $
b00001101 &
b10110 %
b00111101 '
b00001101 (
b00111101 )
#60
0!
#70
1!
b01101 $
b10001100 &
b11001 %
b11000110 '
b10001100 (
b11000110 )
#80
0!
#90
1!
b00101 $
b10101010 &
b00101 %
b01110111 '
b10101010 (
b01110111 )
#100
0!
#110
1!
b10010 $
b10001111 &
b10010 %
b11001110 '
b10001111 (
b11001110 )
#120
0!
#130
1!
b01000 $
b11000101 &
b11100 %
b10111101 '
b11000101 (
b10111101 )
#140
0!
#150
1!
b01101 $
b01100101 &
b00011 %
b00001010 '
b01100101 (
b00001010 )
#160
0!
#170
1!
b00000 $
b00100000 &
b01010 %
b10011101 '
b00100000 (
b10011101 )
