Adder/Adder_design.v
module adder_design(input logic [7:0] a,
input logic [7:0] b,
input logic c_in,
output logic [7:0] sum,
output logic c_out);

assign {c_out, sum}=a+b+c_in;

endmodule: adder_design

Adder/Adder_testbench.sv
// Code your testbench here
module testbench_adder();
logic [7:0] a;
logic [7:0] b;
logic c_in;
logic [7:0] sum;
logic c_out;

//DUT instantiate 
adder_design adder_tb(.a(a), .b(b), .c_in(c_in), .sum(sum), .c_out(c_Out));
 
initial begin
    #10 a=0; b=0; c_in=1;
    #10 a=1; b=0; c_in=1;
    #10 a=0; b=1; c_in=1;
    #10 a=1; b=1; c_in=1;
    
    #10 a=0; b=0; c_in=0;
    #10 a=1; b=0; c_in=0;
    #10 a=1; b=0; c_in=0;
    #10 a=1; b=1; c_in=0;
end
initial begin
    $monitor ($time, "a=%b, b=%b, c_in=%b, sum=%b, c_out=%b", a , b, c_in, sum, c_out);
     
    #100 $finish;
end

initial begin
    $dumpfile("adder.vcd");
    $dumpvars;
end

endmodule: testbench_adder

Adder/adder.vcd
$date
	Sun Oct  1 22:22:35 2023
$end

$version
	Synopsys VCS version S-2021.09
$end

$timescale
	1ns
$end

$comment Csum: 1 f24eb21bf32c5733 $end


$scope module testbench_adder $end
$var reg 8 ! a [7:0] $end
$var reg 8 " b [7:0] $end
$var reg 1 # c_in $end
$var reg 8 $ sum [7:0] $end
$var reg 1 % c_out $end
$var wire 1 & c_Out $end

$scope module adder_tb $end
$var reg 8 ! a [7:0] $end
$var reg 8 " b [7:0] $end
$var reg 1 # c_in $end
$var reg 8 $ sum [7:0] $end
$var reg 1 ' c_out $end
$upscope $end

$upscope $end

$enddefinitions $end

#0
$dumpvars
x#
x'
x&
bxxxxxxxx !
bxxxxxxxx "
bxxxxxxxx $
x%
$end
#10
b00000000 !
0'
0&
b00000000 "
1#
b00000001 $
#20
b00000001 !
b00000010 $
#30
b00000000 !
b00000001 "
#40
b00000001 !
b00000011 $
#50
b00000000 !
b00000000 "
0#
b00000000 $
#60
b00000001 !
b00000001 $
#80
b00000001 "
b00000010 $
