ALU/ALU_design.sv
module ALU_design(out,sign,carr,zero,in);
  output logic [3:0]out; 
  output logic sign,carr,zero; 
  input logic [11:0]in;
  
  logic [3:0]A;
  logic [3:0]B;
  logic [4:0]y;

always@(in)
begin
  A=in[3:0];
  B=in[7:4];
  carr=0;
  sign=0;

  if (y[4:0]==0)zero=1;
  else zero = 0;
  out=y[3:0];
  
  case(in[11:8])
  4'b1101:
     begin
       y=A+B;
       if (y>4'b1111)carr=1;
     end  
  4'b1001:y=A&B;
  4'b0101:y=A[1:0]*B[1:0];
  4'b0001:y=~A;
  4'b1100:y=~(A&B);
  4'b0010:
     begin
        if (B>A)begin
           y=B-A; 
           sign=1;
           end
        else y=A-B;
     end
  4'b0011:y=~(A^B);
  4'b0110:y=~(A|B);
  default y=0;
  endcase
end

endmodule: ALU_design

ALU/ALU_testbench_v1.sv
// Code your testbench here
module ALU_testbench();
  logic [3:0]out; 
  logic sign,carr,zero; 
  logic [11:0]in;
  
//DUT instantiate 
  ALU_design DUT(   .in(in),
                    .sign(sign),
                    .carr(carr),
                    .zero(zero),
                    .out(out));
 /* //clock generating
 initial begin
   logic clk=0;
   forever #5 clk=~clk;
 end */
 
initial begin
  #10 in=12'b000100001100;  //NOT
  #10 in=12'b110110100010; //ADD
  #10 in=12'b100100110101; //AND
  #10 in=12'b010100100010; //MUL
  #10 in=12'b110001110110; //NAND
  #10 in=12'b001010010001; //SUBTRACT with carry
  #10 in=12'b001110110011; //XNOR
  #10 in=12'b011000010100; //NOR
  
  #10 in=12'b111110100000; //default
  #10 in=12'b000010100000; //default 
end
  
initial begin
  #10;
  $monitor ($time," in=%b, out=%b, sign=%b, carr=%b, zero=%b",in,out,carr,sign,zero);

  #130 $finish;
end    
  
initial begin
  $dumpfile("alu.vcd");
  $dumpvars;
end
  
endmodule: ALU_testbench

ALU/alu.vcd
$date
	Mon Oct  2 11:30:34 2023
$end

$version
	Synopsys VCS version S-2021.09
$end

$timescale
	1ns
$end

$comment Csum: 1 c2b0bf3a1e93ce6b $end


$scope module ALU_testbench $end
$var reg 4 ! out [3:0] $end
$var reg 1 " sign $end
$var reg 1 # carr $end
$var reg 1 $ zero $end
$var reg 12 % in [11:0] $end

$scope module DUT $end
$var reg 4 ! out [3:0] $end
$var reg 1 " sign $end
$var reg 1 # carr $end
$var reg 1 $ zero $end
$var reg 12 % in [11:0] $end
$var reg 4 & A [3:0] $end
$var reg 4 ' B [3:0] $end
$var reg 5 ( y [4:0] $end
$upscope $end

$upscope $end

$enddefinitions $end

#0
$dumpvars
x#
x"
x$
bxxxxxxxxxxxx %
bxxxx !
bxxxx &
bxxxx '
bxxxxx (
$end
#10
b000100001100 %
b1100 &
b0000 '
0#
0"
0$
b10011 (
#20
b110110100010 %
b0010 &
b1010 '
b0011 !
b01100 (
#30
b100100110101 %
b0101 &
b0011 '
b1100 !
b00001 (
#40
b010100100010 %
b0010 &
b0010 '
b0001 !
b00100 (
#50
b110001110110 %
b0110 &
b0111 '
b0100 !
b11001 (
#60
b001010010001 %
b0001 &
b1001 '
1"
b1001 !
b01000 (
#70
b001110110011 %
b0011 &
b1011 '
0"
b1000 !
b10111 (
#80
b011000010100 %
b0100 &
b0001 '
b0111 !
b11010 (
#90
b111110100000 %
b0000 &
b1010 '
b1010 !
b00000 (
#100
b000010100000 %
1$
b0000 !
